spiceweasel/__init__.py
spiceweasel/ekf.py
spiceweasel/jacobian.py
spiceweasel-0.0.3.dist-info/LICENSE
spiceweasel-0.0.3.dist-info/WHEEL
spiceweasel-0.0.3.dist-info/METADATA
spiceweasel-0.0.3.dist-info/RECORD
