Metadata-Version: 2.1
Name: spiceweasel
Version: 0.0.3
Summary: Kalman filter stuff
Home-page: https://pypi.org/project/spiceweasel/
License: MIT
Keywords: ekf,kf,filter,kalman
Author: walchko
Author-email: walchko@users.noreply.github.com
Requires-Python: >=3.8
Classifier: Development Status :: 4 - Beta
Classifier: Intended Audience :: Developers
Classifier: License :: OSI Approved :: MIT License
Classifier: Operating System :: OS Independent
Classifier: Programming Language :: Python :: 3
Classifier: Programming Language :: Python :: 3.10
Classifier: Programming Language :: Python :: 3.8
Classifier: Programming Language :: Python :: 3.9
Classifier: Topic :: Software Development :: Libraries
Classifier: Topic :: Software Development :: Libraries :: Application Frameworks
Classifier: Topic :: Software Development :: Libraries :: Python Modules
Requires-Dist: numpy
Requires-Dist: pyrk
Project-URL: Repository, https://github.com/MomsFriendlyRobotCompany/spiceweasel
